LICENSE.md
README.md
pyproject.toml
src/ewoksid24/__init__.py
src/ewoksid24/init_matplotlib.py
src/ewoksid24.egg-info/PKG-INFO
src/ewoksid24.egg-info/SOURCES.txt
src/ewoksid24.egg-info/dependency_links.txt
src/ewoksid24.egg-info/entry_points.txt
src/ewoksid24.egg-info/requires.txt
src/ewoksid24.egg-info/top_level.txt
src/ewoksid24/apps/__init__.py
src/ewoksid24/apps/xasmap_viewer.py
src/ewoksid24/gui/__init__.py
src/ewoksid24/gui/settings.py
src/ewoksid24/gui/xasmap_select.py
src/ewoksid24/gui/xasmap_viewer.py
src/ewoksid24/io/__init__.py
src/ewoksid24/io/bliss.py
src/ewoksid24/io/temperature.py
src/ewoksid24/io/xas.py
src/ewoksid24/io/xasmap.py
src/ewoksid24/math/__init__.py
src/ewoksid24/math/planck.py
src/ewoksid24/math/xasmap.py
src/ewoksid24/plots/__init__.py
src/ewoksid24/plots/temperature.py
src/ewoksid24/plots/xas.py
src/ewoksid24/tasks/__init__.py
src/ewoksid24/tasks/fit.py
src/ewoksid24/tasks/plot.py
src/ewoksid24/tasks/read.py
src/ewoksid24/tests/__init__.py
src/ewoksid24/tests/conftest.py
src/ewoksid24/tests/test_fit.py
src/ewoksid24/tests/test_io.py
src/ewoksid24/tests/test_temperature.py
src/ewoksid24/tests/test_xasmap.py
src/ewoksid24/tests/data/__init__.py
src/ewoksid24/tests/data/xanes.h5
src/ewoksid24/tests/gui/__init__.py
src/ewoksid24/tests/gui/test_xasmap_select.py
src/ewoksid24/tests/gui/test_xasmap_viewer.py